promptstudio_sdk/__init__.py
promptstudio_sdk/base.py
promptstudio_sdk/cache.py
promptstudio_sdk/client.py
promptstudio_sdk/exception.py
promptstudio_sdk/persistent_cache.py
promptstudio_sdk/prompt.py
promptstudio_sdk/types.py
promptstudio_sdk/utils/__init__.py
promptstudio_sdk/utils/helpers.py
promptstudio_sdk/utils/logger.py
promptstudio_sdk-1.0.254.dist-info/METADATA
promptstudio_sdk-1.0.254.dist-info/WHEEL
promptstudio_sdk-1.0.254.dist-info/top_level.txt
promptstudio_sdk-1.0.254.dist-info/RECORD
