Metadata-Version: 2.4
Name: promptstudio_sdk
Version: 1.0.254
Summary: A Python SDK for PromptStudio
Home-page: https://github.com/promptstudio-dev/promptstudio-sdk-python
Author: PromptStudio
Author-email: support@promptstudio.dev
Classifier: Programming Language :: Python :: 3
Classifier: License :: OSI Approved :: MIT License
Classifier: Operating System :: OS Independent
Requires-Python: >=3.8
Requires-Dist: requests
Requires-Dist: pymongo
Requires-Dist: openai
Requires-Dist: anthropic
Requires-Dist: google-genai
Provides-Extra: test
Requires-Dist: pytest; extra == "test"
Requires-Dist: pytest-cov; extra == "test"
Dynamic: author-email
Dynamic: home-page
Dynamic: requires-python
